ontoenv-0.4.0.dist-info/METADATA
ontoenv-0.4.0.dist-info/WHEEL
ontoenv-0.4.0.dist-info/entry_points.txt
ontoenv.libs/libgcc_s-2d945d6c.so.1
ontoenv.libs/libstdc++-85f2cd6d.so.6
ontoenv/__init__.py
ontoenv/_cli.py
ontoenv/_native.abi3.so
ontoenv-0.4.0.dist-info/RECORD
