Metadata-Version: 2.4
Name: ontoenv
Version: 0.4.0
Requires-Dist: oxrdflib>=0.4.0
Requires-Dist: rdflib>=7.1.3
Summary: Python bindings for the OntoEnv Rust library. Manages ontology-based environments for building knowledge graphs.
Home-Page: https://github.com/gtfierro/ontoenv-rs
Author-email: Gabe Fierro <gtfierro@mines.edu>
License-Expression: bsd-3-clause
Requires-Python: >=3.11
